pygame_ai/__init__.py
pygame_ai/colors.py
pygame_ai/gameobject.py
pygame_ai/steering/__init__.py
pygame_ai/steering/blended.py
pygame_ai/steering/kinematic.py
pygame_ai/steering/path.py
pygame_ai/steering/priority.py
pygame_ai/steering/static.py
pygame_ai/tests/__init__.py
pygame_ai/tests/test_joke.py
pygame_ai/utils/__init__.py
pygame_ai/utils/list_utils.py
pygame_ai/utils/math_utils.py
pygame_ai-0.1.2.dist-info/LICENSE
pygame_ai-0.1.2.dist-info/METADATA
pygame_ai-0.1.2.dist-info/WHEEL
pygame_ai-0.1.2.dist-info/top_level.txt
pygame_ai-0.1.2.dist-info/RECORD
